my_cli_utilities-0.4.7.dist-info/licenses/LICENSE
rc_cli/__init__.py
rc_cli/cli.py
rc_cli/common.py
rc_cli/config_commands.py
rc_cli/env_loader.py
rc_cli/tui_clipboard.py
rc_cli/tui_common.py
rc_cli/tui_css_common.py
rc_cli/tui_prefill.py
rc_cli/unified_tui.py
rc_cli/account_pool/__init__.py
rc_cli/account_pool/alias_mapping_service.py
rc_cli/account_pool/commands.py
rc_cli/account_pool/data_manager.py
rc_cli/account_pool/display_manager.py
rc_cli/account_pool/resolvers.py
rc_cli/account_pool/result_types.py
rc_cli/account_pool/service.py
rc_cli/account_pool/tui.py
rc_cli/account_pool/tui_components/__init__.py
rc_cli/account_pool/tui_components/app.py
rc_cli/account_pool/tui_components/base.py
rc_cli/account_pool/tui_components/constants.py
rc_cli/account_pool/tui_components/get_by_alias.py
rc_cli/account_pool/tui_components/get_by_phone.py
rc_cli/account_pool/tui_components/list_aliases.py
rc_cli/account_pool/tui_components/menu.py
rc_cli/account_pool/tui_components/modal.py
rc_cli/common/__init__.py
rc_cli/common/company_config.py
rc_cli/common/config.py
rc_cli/common/service_factory.py
rc_cli/common/utils.py
rc_cli/common_lib/__init__.py
rc_cli/common_lib/config.py
rc_cli/common_lib/config_base.py
rc_cli/common_lib/config_modules.py
rc_cli/common_lib/http_helpers.py
rc_cli/common_lib/jenkins_helpers.py
rc_cli/common_lib/pagination.py
rc_cli/common_lib/system_helpers.py
rc_cli/device_spy/__init__.py
rc_cli/device_spy/cli_commands.py
rc_cli/device_spy/commands.py
rc_cli/device_spy/commands_core.py
rc_cli/device_spy/connection_services.py
rc_cli/device_spy/data_manager.py
rc_cli/device_spy/display_managers.py
rc_cli/device_spy/host_display.py
rc_cli/device_spy/result_types.py
rc_cli/device_spy/connection/__init__.py
rc_cli/device_spy/connection/credentials.py
rc_cli/device_spy/connection/executor.py
rc_cli/device_spy/connection/host_resolver.py
rc_cli/device_spy/connection/manager.py
rc_cli/device_spy/connection/types.py
rc_cli/device_spy/connection/validators.py
rc_cli/device_spy/tui/__init__.py
my_cli_utilities-0.4.7.dist-info/METADATA
my_cli_utilities-0.4.7.dist-info/WHEEL
my_cli_utilities-0.4.7.dist-info/entry_points.txt
my_cli_utilities-0.4.7.dist-info/top_level.txt
my_cli_utilities-0.4.7.dist-info/RECORD
