Metadata-Version: 2.4
Name: my-cli-utilities
Version: 0.4.7
Summary: A suite of CLI utilities for account pool and device spy services.
Author-email: Swain Zheng <swain.zheng@xxxx.com>
License-Expression: MIT
Project-URL: Homepage, https://github.com/yourusername/my-cli-utilities
Project-URL: Bug Tracker, https://github.com/yourusername/my-cli-utilities/issues
Classifier: Programming Language :: Python :: 3
Classifier: Operating System :: OS Independent
Classifier: Development Status :: 3 - Alpha
Classifier: Intended Audience :: Developers
Classifier: Topic :: Utilities
Requires-Python: >=3.10
License-File: LICENSE
Requires-Dist: httpx>=0.20
Requires-Dist: fire>=0.4
Requires-Dist: typer>=0.9.0
Requires-Dist: icecream>=2.1.0
Requires-Dist: tqdm>=4.60.0
Requires-Dist: psutil>=5.9.0
Requires-Dist: py-cpuinfo>=9.0.0
Requires-Dist: distro>=1.8.0
Requires-Dist: returns>=0.25.0
Requires-Dist: textual>=0.40.0
Requires-Dist: pyyaml>=6.0
Requires-Dist: pyperclip>=1.8.0
Provides-Extra: dev
Requires-Dist: build>=1.0.0; extra == "dev"
Requires-Dist: twine>=4.0.0; extra == "dev"
Dynamic: license-file
